setup.py
docker_debug.egg-info/PKG-INFO
docker_debug.egg-info/SOURCES.txt
docker_debug.egg-info/dependency_links.txt
docker_debug.egg-info/entry_points.txt
docker_debug.egg-info/requires.txt
docker_debug.egg-info/top_level.txt
dockerdebug/__init__.py
dockerdebug/main.py
dockerdebug/run.py
dockerdebug/tail.py