Metadata-Version: 1.0
Name: docker-debug
Version: 1.2.1
Summary: Docker container debugging tool
Home-page: http://locationlabs.com
Author: Location Labs
Author-email: info@locationlabs.com
License: UNKNOWN
Platform: UNKNOWN
